<?xml version="1.0"?>
<!DOCTYPE hibernate-mapping PUBLIC "-//Hibernate/Hibernate Mapping DTD 3.0//EN"
"http://hibernate.sourceforge.net/hibernate-mapping-3.0.dtd">
<!-- Generated 2017-4-25 21:34:41 by Hibernate Tools 3.5.0.Final -->
<hibernate-mapping>
    <class name="com.anbang.po.Department" table="department">
        <id name="id" type="java.lang.String">
            <column name="ID" />
            <generator class="uuid" />
        </id>
        <property name="deptName" type="java.lang.String">
            <column name="DEPTNAME" />
        </property>
        <property name="deptDesc" type="java.lang.String">
            <column name="DEPTDESC" />
        </property>
    </class>
</hibernate-mapping>
